display_xml/__init__.py
display_xml/_version.py
display_xml/xml.py
display_xml-0.1.0.dist-info/DESCRIPTION.rst
display_xml-0.1.0.dist-info/METADATA
display_xml-0.1.0.dist-info/RECORD
display_xml-0.1.0.dist-info/WHEEL
display_xml-0.1.0.dist-info/metadata.json
display_xml-0.1.0.dist-info/top_level.txt
