Metadata-Version: 2.0
Name: display-xml
Version: 0.1.0
Summary: Prettier XML in IPython/Jupyter display contexts.
Home-page: https://github.com/mpacer/display_xml
Author: M Pacer
Author-email: mpacer@berkeley.edu
License: BSD
Keywords: Jupyter,JupyterLab,XML
Platform: Linux
Platform: Mac OS X
Platform: Windows
Classifier: Intended Audience :: Developers
Classifier: Intended Audience :: Science/Research
Classifier: License :: OSI Approved :: BSD License
Classifier: Programming Language :: Python
Classifier: Programming Language :: Python :: 3
Requires-Python: >=3.6
Requires-Dist: ipython (>=6.2.1)
Requires-Dist: pygments (>=2.2.0)
Requires-Dist: lxml (>=4.1.1)
